setup.py
pynyti/__init__.py
pynyti.egg-info/PKG-INFO
pynyti.egg-info/SOURCES.txt
pynyti.egg-info/dependency_links.txt
pynyti.egg-info/top_level.txt