Metadata-Version: 2.1
Name: pynyti
Version: 0.1.0
Summary: PyNy
Author: TheCoderCat
Author-email: cyrus.g.russell@gmail.com
Classifier: Programming Language :: Python :: 3
Classifier: License :: OSI Approved :: MIT License
Classifier: Operating System :: OS Independent
Requires-Python: >=3.6
